LICENSE
MANIFEST.in
README.rst
requirements.txt
setup.py
src/scaffy/__init__.py
src/scaffy/config.py
src/scaffy/main.py
src/scaffy.egg-info/PKG-INFO
src/scaffy.egg-info/SOURCES.txt
src/scaffy.egg-info/dependency_links.txt
src/scaffy.egg-info/entry_points.txt
src/scaffy.egg-info/requires.txt
src/scaffy.egg-info/top_level.txt
src/scaffy/commands/__init__.py
src/scaffy/commands/local.py
src/scaffy/commands/remote.py
src/scaffy/commands/scaffold.py
src/scaffy/core/__init__.py
src/scaffy/core/config.py
src/scaffy/core/const.py
src/scaffy/core/fs.py
src/scaffy/core/git.py
src/scaffy/core/log.py
src/scaffy/core/shell.py
src/scaffy/remote/__init__.py
src/scaffy/remote/scaffold.py
src/scaffy/remote/util.py
src/scaffy/scaffold/__init__.py
src/scaffy/scaffold/local.py
src/scaffy/scaffold/scaffold.py