Metadata-Version: 1.1
Name: scaffy
Version: 0.8.2
Summary: Set of CLI commands for project scaffolds
Home-page: http://github.com/novopl/scaffy
Author: Mateusz 'novo' Klos
Author-email: novopl@gmail.com
License: MIT
Keywords: project scaffold dev tools
Platform: UNKNOWN
Classifier: Development Status :: 4 - Beta
Classifier: Topic :: Utilities
Classifier: Intended Audience :: Developers
Classifier: Programming Language :: Python
Classifier: License :: OSI Approved :: MIT License
